netspecs/__init__.py
netspecs/cli.py
netspecs/agent/__init__.py
netspecs/agent/analyst.py
netspecs/agent/prompts.py
netspecs/core/__init__.py
netspecs/core/bufferbloat.py
netspecs/core/connectivity.py
netspecs/core/jitter.py
netspecs/core/latency.py
netspecs/core/monitor.py
netspecs/core/network_info.py
netspecs/core/prioritization.py
netspecs/core/speed.py
netspecs/reporters/__init__.py
netspecs/reporters/console.py
netspecs/reporters/csv.py
netspecs/reporters/json.py
netspecs/utils/__init__.py
netspecs/utils/config.py
netspecs/utils/platform.py
netspecs/web/__init__.py
netspecs/web/server.py
netspecs/web/static/index.html
netspecs/web/static/netspecs-icon.png
netspecs/web/static/css/styles.css
netspecs/web/static/js/app.js
netspecs-0.1.0.dist-info/licenses/LICENSE
netspecs-0.1.0.dist-info/METADATA
netspecs-0.1.0.dist-info/WHEEL
netspecs-0.1.0.dist-info/entry_points.txt
netspecs-0.1.0.dist-info/top_level.txt
netspecs-0.1.0.dist-info/RECORD
